image_processing/__init__.py
image_processing/processing/__init__.py
image_processing/processing/combination.py
image_processing/processing/transformation.py
image_processing/utils/__init__.py
image_processing/utils/io.py
image_processing/utils/plot.py
wqferr_image_processing/__init__.py
wqferr_image_processing/processing/__init__.py
wqferr_image_processing/processing/combination.py
wqferr_image_processing/processing/transformation.py
wqferr_image_processing/utils/__init__.py
wqferr_image_processing/utils/io.py
wqferr_image_processing/utils/plot.py
wqferr_image_processing-0.1.1.dist-info/METADATA
wqferr_image_processing-0.1.1.dist-info/WHEEL
wqferr_image_processing-0.1.1.dist-info/top_level.txt
wqferr_image_processing-0.1.1.dist-info/RECORD
