Metadata-Version: 2.1
Name: wqferr_image_processing
Version: 0.1.1
Summary: An example package wrapping simple functionality from skimage.
Home-page: https://github.com/wqferr/trilha-python-dio-image-processing-package
Author: William Q Ferreira
Author-email: wqferr@gmail.com
Requires-Python: >=3.8
Requires-Dist: scikit-image>=0.25.1
Requires-Dist: matplotlib>=3.10.0
